[
  {
    "id": "1766543031241-432896",
    "message": "Card movido: Grizzales → coluna 2",
    "cardId": 7,
    "toColumnId": 2,
    "timestamp": 1766543031241,
    "read": true
  },
  {
    "id": "1766543031557-246883",
    "message": "Card movido: Grizzales → coluna 2",
    "cardId": 7,
    "toColumnId": 2,
    "timestamp": 1766543031557,
    "read": true
  },
  {
    "id": "1766543038386-359221",
    "message": "Card movido: Grizzales → coluna 3",
    "cardId": 6,
    "toColumnId": 3,
    "timestamp": 1766543038386,
    "read": true
  },
  {
    "id": "1766544795424-446873",
    "message": "Card movido: Grizzales → coluna 4",
    "cardId": 6,
    "toColumnId": 4,
    "timestamp": 1766544795424,
    "read": true
  },
  {
    "id": "1766545321652-220644",
    "message": "Card movido: Grizzales → coluna 3",
    "cardId": 7,
    "toColumnId": 3,
    "timestamp": 1766545321652,
    "read": false
  },
  {
    "id": "1766545326959-473075",
    "message": "Card movido: Grizzales → coluna 5",
    "cardId": 6,
    "toColumnId": 5,
    "timestamp": 1766545326959,
    "read": false
  },
  {
    "id": "1766545338806-244625",
    "message": "Card movido: Grizzales → coluna 1",
    "cardId": 7,
    "toColumnId": 1,
    "timestamp": 1766545338806,
    "read": false
  },
  {
    "id": "1766545342477-993734",
    "message": "Card movido: Grizzales → coluna 1",
    "cardId": 6,
    "toColumnId": 1,
    "timestamp": 1766545342477,
    "read": false
  },
  {
    "id": "1766545342794-259005",
    "message": "Card movido: Grizzales → coluna 1",
    "cardId": 6,
    "toColumnId": 1,
    "timestamp": 1766545342794,
    "read": true
  },
  {
    "id": "1766545463206-290482",
    "message": "Card movido: Grizzales → coluna 2",
    "cardId": 7,
    "toColumnId": 2,
    "timestamp": 1766545463206,
    "read": false
  },
  {
    "id": "1766545625460-858604",
    "message": "Card movido: Grizzales → coluna 1",
    "cardId": 7,
    "toColumnId": 1,
    "timestamp": 1766545625460,
    "read": false
  },
  {
    "id": "1766545625775-919325",
    "message": "Card movido: Grizzales → coluna 1",
    "cardId": 7,
    "toColumnId": 1,
    "timestamp": 1766545625775,
    "read": true
  },
  {
    "id": "1766546021121-353566",
    "message": "Card movido: Grizzales → coluna 2",
    "cardId": 7,
    "toColumnId": 2,
    "timestamp": 1766546021121,
    "read": false
  },
  {
    "id": "1766546023934-627910",
    "message": "Card movido: Grizzales → coluna 2",
    "cardId": 6,
    "toColumnId": 2,
    "timestamp": 1766546023934,
    "read": false
  },
  {
    "id": "1766546024261-107239",
    "message": "Card movido: Grizzales → coluna 2",
    "cardId": 6,
    "toColumnId": 2,
    "timestamp": 1766546024261,
    "read": false
  },
  {
    "id": "1766546037272-320362",
    "message": "Card movido: Grizzales → coluna 2",
    "cardId": 7,
    "toColumnId": 2,
    "timestamp": 1766546037272,
    "read": false
  },
  {
    "id": "1766546037585-650188",
    "message": "Card movido: Grizzales → coluna 2",
    "cardId": 7,
    "toColumnId": 2,
    "timestamp": 1766546037585,
    "read": false
  },
  {
    "id": "1766546494353-440993",
    "message": "Card movido: Grizzales → coluna 1",
    "cardId": 7,
    "toColumnId": 1,
    "timestamp": 1766546494353,
    "read": false
  },
  {
    "id": "1766546495380-658151",
    "message": "Card movido: Grizzales → coluna 1",
    "cardId": 6,
    "toColumnId": 1,
    "timestamp": 1766546495380,
    "read": false
  },
  {
    "id": "1766546495709-960557",
    "message": "Card movido: Grizzales → coluna 1",
    "cardId": 6,
    "toColumnId": 1,
    "timestamp": 1766546495709,
    "read": false
  },
  {
    "id": "1766546506829-556523",
    "message": "Card movido: Grizzales → coluna 2",
    "cardId": 7,
    "toColumnId": 2,
    "timestamp": 1766546506829,
    "read": false
  },
  {
    "id": "1766546507757-034416",
    "message": "Card movido: Grizzales → coluna 2",
    "cardId": 6,
    "toColumnId": 2,
    "timestamp": 1766546507757,
    "read": false
  },
  {
    "id": "1766546508064-920126",
    "message": "Card movido: Grizzales → coluna 2",
    "cardId": 6,
    "toColumnId": 2,
    "timestamp": 1766546508064,
    "read": true
  },
  {
    "id": "1766547666665-614202",
    "message": "Card movido: Grizzales → coluna 3",
    "cardId": 7,
    "toColumnId": 3,
    "timestamp": 1766547666665,
    "read": false
  },
  {
    "id": "1766547670684-135995",
    "message": "Card movido: Grizzales → coluna 3",
    "cardId": 6,
    "toColumnId": 3,
    "timestamp": 1766547670684,
    "read": false
  },
  {
    "id": "1766547671005-031382",
    "message": "Card movido: Grizzales → coluna 3",
    "cardId": 6,
    "toColumnId": 3,
    "timestamp": 1766547671005,
    "read": false
  },
  {
    "id": "1766547827272-123853",
    "message": "Card movido: Grizzales → coluna 2",
    "cardId": 7,
    "toColumnId": 2,
    "timestamp": 1766547827272,
    "read": false
  },
  {
    "id": "1766547829734-202946",
    "message": "Card movido: Grizzales → coluna 2",
    "cardId": 6,
    "toColumnId": 2,
    "timestamp": 1766547829734,
    "read": false
  },
  {
    "id": "1766547830090-894846",
    "message": "Card movido: Grizzales → coluna 2",
    "cardId": 6,
    "toColumnId": 2,
    "timestamp": 1766547830090,
    "read": false
  },
  {
    "id": "1766547862030-409837",
    "message": "Card movido: Grizzales → coluna 1",
    "cardId": 7,
    "toColumnId": 1,
    "timestamp": 1766547862030,
    "read": false
  },
  {
    "id": "1766547863564-705352",
    "message": "Card movido: Grizzales → coluna 1",
    "cardId": 6,
    "toColumnId": 1,
    "timestamp": 1766547863564,
    "read": false
  },
  {
    "id": "1766547863900-300792",
    "message": "Card movido: Grizzales → coluna 1",
    "cardId": 6,
    "toColumnId": 1,
    "timestamp": 1766547863900,
    "read": false
  },
  {
    "id": "1766547931407-227113",
    "message": "Card movido: Grizzales → coluna 2",
    "cardId": 7,
    "toColumnId": 2,
    "timestamp": 1766547931407,
    "read": false
  },
  {
    "id": "1766548140328-304444",
    "message": "Card movido: Grizzales → coluna 2",
    "cardId": 6,
    "toColumnId": 2,
    "timestamp": 1766548140328,
    "read": false
  },
  {
    "id": "1766548140662-067452",
    "message": "Card movido: Grizzales → coluna 2",
    "cardId": 6,
    "toColumnId": 2,
    "timestamp": 1766548140662,
    "read": false
  },
  {
    "id": "1766548446026-005360",
    "message": "Card movido: Grizzales → coluna 1",
    "cardId": 7,
    "toColumnId": 1,
    "timestamp": 1766548446026,
    "read": false
  },
  {
    "id": "1766548731676-013630",
    "message": "Card movido: Grizzales → coluna 3",
    "cardId": 6,
    "toColumnId": 3,
    "timestamp": 1766548731676,
    "read": true
  },
  {
    "id": "1766548839587-910638",
    "message": "Card movido: Grizzales → coluna 2",
    "cardId": 6,
    "toColumnId": 2,
    "timestamp": 1766548839587,
    "read": true
  },
  {
    "id": "1766577687303-196735",
    "message": "Card movido: UBVA - IA → coluna 11",
    "cardId": 1,
    "toColumnId": 11,
    "timestamp": 1766577687303,
    "read": false
  },
  {
    "id": "1766577688276-234858",
    "message": "Card movido: UBVA - IA → coluna 11",
    "cardId": 1,
    "toColumnId": 11,
    "timestamp": 1766577688276,
    "read": false
  },
  {
    "id": "1766577688735-088789",
    "message": "Card movido: UBVA - IA → coluna 11",
    "cardId": 1,
    "toColumnId": 11,
    "timestamp": 1766577688735,
    "read": false
  },
  {
    "id": "1766577692735-475730",
    "message": "Card movido: UBVA - IA → coluna 10",
    "cardId": 1,
    "toColumnId": 10,
    "timestamp": 1766577692735,
    "read": true
  },
  {
    "id": "1766577728632-396289",
    "message": "Card movido: UBVA - IA → coluna 11",
    "cardId": 1,
    "toColumnId": 11,
    "timestamp": 1766577728632,
    "read": false
  },
  {
    "id": "1766577734363-925561",
    "message": "Card movido: UBVA - IA → coluna 12",
    "cardId": 1,
    "toColumnId": 12,
    "timestamp": 1766577734363,
    "read": false
  },
  {
    "id": "1766578087542-869595",
    "message": "Card movido: UBVA - IA → coluna 10",
    "cardId": 1,
    "toColumnId": 10,
    "timestamp": 1766578087542,
    "read": false
  },
  {
    "id": "1766578507457-897110",
    "message": "Card movido: TREKSTAR → coluna 11",
    "cardId": 2,
    "toColumnId": 11,
    "timestamp": 1766578507457,
    "read": false
  },
  {
    "id": "1766578671397-049730",
    "message": "Card movido: TREKSTAR → coluna 12",
    "cardId": 2,
    "toColumnId": 12,
    "timestamp": 1766578671397,
    "read": false
  },
  {
    "id": "1766578675362-162761",
    "message": "Card movido: TREKSTAR → coluna 11",
    "cardId": 2,
    "toColumnId": 11,
    "timestamp": 1766578675362,
    "read": false
  },
  {
    "id": "1766578679985-212765",
    "message": "Card movido: UBVA - IA → coluna 11",
    "cardId": 1,
    "toColumnId": 11,
    "timestamp": 1766578679985,
    "read": false
  },
  {
    "id": "1766578680512-651016",
    "message": "Card movido: UBVA - IA → coluna 11",
    "cardId": 1,
    "toColumnId": 11,
    "timestamp": 1766578680512,
    "read": false
  },
  {
    "id": "1766578683343-963889",
    "message": "Card movido: TREKSTAR → coluna 12",
    "cardId": 2,
    "toColumnId": 12,
    "timestamp": 1766578683343,
    "read": false
  },
  {
    "id": "1766578751955-309787",
    "message": "Card movido: TREKSTAR → coluna 13",
    "cardId": 2,
    "toColumnId": 13,
    "timestamp": 1766578751955,
    "read": false
  },
  {
    "id": "1766579718121-135173",
    "message": "Card movido em \"UBVA - IA\": TREKSTAR → Levantamento de Requisitos",
    "cardId": 2,
    "toColumnId": 11,
    "timestamp": 1766579718121,
    "read": false
  },
  {
    "id": "1766579718155-929234",
    "message": "Card movido em \"UBVA - IA\": TREKSTAR → Levantamento de Requisitos",
    "cardId": 2,
    "toColumnId": 11,
    "timestamp": 1766579718155,
    "read": false
  },
  {
    "id": "1766579734639-259802",
    "message": "Card movido em \"UBVA - IA\": UBVA - IA → Backlog",
    "cardId": 1,
    "toColumnId": 10,
    "timestamp": 1766579734639,
    "read": false
  },
  {
    "id": "1766579735690-764668",
    "message": "Card movido em \"UBVA - IA\": TREKSTAR → Backlog",
    "cardId": 2,
    "toColumnId": 10,
    "timestamp": 1766579735690,
    "read": false
  },
  {
    "id": "1766579735716-983675",
    "message": "Card movido em \"UBVA - IA\": TREKSTAR → Backlog",
    "cardId": 2,
    "toColumnId": 10,
    "timestamp": 1766579735716,
    "read": false
  },
  {
    "id": "1766580057967-940275",
    "message": "Card movido em \"UBVA - IA\": UBVA - IA → Levantamento de Requisitos",
    "cardId": 1,
    "toColumnId": 11,
    "timestamp": 1766580057967,
    "read": false
  },
  {
    "id": "1766580061363-922341",
    "message": "Card movido em \"UBVA - IA\": UBVA - IA → Backlog",
    "cardId": 1,
    "toColumnId": 10,
    "timestamp": 1766580061363,
    "read": false
  },
  {
    "id": "1766580061392-697008",
    "message": "Card movido em \"UBVA - IA\": UBVA - IA → Backlog",
    "cardId": 1,
    "toColumnId": 10,
    "timestamp": 1766580061392,
    "read": false
  },
  {
    "id": "1766580473861-513073",
    "message": "Card movido em \"UBVA - IA\": UBVA - IA → Levantamento de Requisitos",
    "cardId": 1,
    "toColumnId": 11,
    "timestamp": 1766580473861,
    "read": false
  },
  {
    "id": "1766580477170-002859",
    "message": "Card movido em \"UBVA - IA\": TREKSTAR → Levantamento de Requisitos",
    "cardId": 2,
    "toColumnId": 11,
    "timestamp": 1766580477170,
    "read": false
  },
  {
    "id": "1766580477197-965523",
    "message": "Card movido em \"UBVA - IA\": TREKSTAR → Levantamento de Requisitos",
    "cardId": 2,
    "toColumnId": 11,
    "timestamp": 1766580477197,
    "read": false
  },
  {
    "id": "1766580481702-311648",
    "message": "Card movido em \"UBVA - IA\": TREKSTAR → Planejamento",
    "cardId": 2,
    "toColumnId": 12,
    "timestamp": 1766580481702,
    "read": false
  },
  {
    "id": "1766580678742-545503",
    "message": "Card movido em \"UBVA - IA\": UBVA - IA → Backlog",
    "cardId": 1,
    "toColumnId": 10,
    "timestamp": 1766580678742,
    "read": false
  },
  {
    "id": "1766580682545-244109",
    "message": "Card movido em \"UBVA - IA\": TREKSTAR → Backlog",
    "cardId": 2,
    "toColumnId": 10,
    "timestamp": 1766580682545,
    "read": false
  },
  {
    "id": "1766580682573-149537",
    "message": "Card movido em \"UBVA - IA\": TREKSTAR → Backlog",
    "cardId": 2,
    "toColumnId": 10,
    "timestamp": 1766580682573,
    "read": false
  },
  {
    "id": "1766580690742-926059",
    "message": "Card movido em \"UBVA - IA\": UBVA - IA → Levantamento de Requisitos",
    "cardId": 1,
    "toColumnId": 11,
    "timestamp": 1766580690742,
    "read": false
  },
  {
    "id": "1766580691788-371085",
    "message": "Card movido em \"UBVA - IA\": TREKSTAR → Levantamento de Requisitos",
    "cardId": 2,
    "toColumnId": 11,
    "timestamp": 1766580691788,
    "read": false
  },
  {
    "id": "1766580691812-185768",
    "message": "Card movido em \"UBVA - IA\": TREKSTAR → Levantamento de Requisitos",
    "cardId": 2,
    "toColumnId": 11,
    "timestamp": 1766580691812,
    "read": false
  },
  {
    "id": "1766580695167-536271",
    "message": "Card movido em \"UBVA - IA\": TREKSTAR → Planejamento",
    "cardId": 2,
    "toColumnId": 12,
    "timestamp": 1766580695167,
    "read": false
  },
  {
    "id": "1766580699830-860356",
    "message": "Card movido em \"UBVA - IA\": TREKSTAR → Design UI/UX",
    "cardId": 2,
    "toColumnId": 13,
    "timestamp": 1766580699830,
    "read": false
  },
  {
    "id": "1766580707821-488304",
    "message": "Card movido em \"UBVA - IA\": TREKSTAR → Desenvolvimento",
    "cardId": 2,
    "toColumnId": 14,
    "timestamp": 1766580707821,
    "read": true
  }
]